[{"Player":"matt g","CommunityID":5,"Disconnectedness":0.9782081863,"AvgDisconnectedness":0.5246725369},{"Player":"glenn z","CommunityID":5,"Disconnectedness":0.9748007944,"AvgDisconnectedness":0.5246725369},{"Player":"john k","CommunityID":5,"Disconnectedness":0.9729863621,"AvgDisconnectedness":0.5246725369},{"Player":"nate l","CommunityID":5,"Disconnectedness":0.9724063934,"AvgDisconnectedness":0.5246725369},{"Player":"becca r","CommunityID":5,"Disconnectedness":0.9715753103,"AvgDisconnectedness":0.5246725369},{"Player":"matt petermann","CommunityID":5,"Disconnectedness":0.9715753103,"AvgDisconnectedness":0.5246725369},{"Player":"alex e","CommunityID":5,"Disconnectedness":0.9715716005,"AvgDisconnectedness":0.5246725369},{"Player":"yeng t","CommunityID":5,"Disconnectedness":0.9715716005,"AvgDisconnectedness":0.5246725369},{"Player":"fritz p","CommunityID":5,"Disconnectedness":0.9713793945,"AvgDisconnectedness":0.5246725369},{"Player":"john p","CommunityID":5,"Disconnectedness":0.9710823025,"AvgDisconnectedness":0.5246725369},{"Player":"anthony m","CommunityID":5,"Disconnectedness":0.970923609,"AvgDisconnectedness":0.5246725369},{"Player":"devin v","CommunityID":5,"Disconnectedness":0.9694438692,"AvgDisconnectedness":0.5246725369},{"Player":"oz dog","CommunityID":5,"Disconnectedness":0.9684529323,"AvgDisconnectedness":0.5246725369},{"Player":"tim n","CommunityID":5,"Disconnectedness":0.9684529323,"AvgDisconnectedness":0.5246725369},{"Player":"joey w","CommunityID":5,"Disconnectedness":0.9671824761,"AvgDisconnectedness":0.5246725369},{"Player":"wayne l","CommunityID":5,"Disconnectedness":0.9643027216,"AvgDisconnectedness":0.5246725369},{"Player":"adam w","CommunityID":5,"Disconnectedness":0.956207314,"AvgDisconnectedness":0.5246725369},{"Player":"charlie p","CommunityID":5,"Disconnectedness":0.956207314,"AvgDisconnectedness":0.5246725369},{"Player":"james k","CommunityID":5,"Disconnectedness":0.956207314,"AvgDisconnectedness":0.5246725369},{"Player":"jeremy m","CommunityID":5,"Disconnectedness":0.956207314,"AvgDisconnectedness":0.5246725369},{"Player":"walker w","CommunityID":5,"Disconnectedness":0.956207314,"AvgDisconnectedness":0.5246725369},{"Player":"joe graham","CommunityID":5,"Disconnectedness":0.4906173684,"AvgDisconnectedness":0.5246725369},{"Player":"rob c","CommunityID":5,"Disconnectedness":0.4864905923,"AvgDisconnectedness":0.5246725369},{"Player":"rickey j","CommunityID":5,"Disconnectedness":0.4831540448,"AvgDisconnectedness":0.5246725369},{"Player":"bryon p","CommunityID":5,"Disconnectedness":0.4816926189,"AvgDisconnectedness":0.5246725369},{"Player":"tim j","CommunityID":5,"Disconnectedness":0.4816265539,"AvgDisconnectedness":0.5246725369},{"Player":"johnny j","CommunityID":5,"Disconnectedness":0.3209028302,"AvgDisconnectedness":0.5246725369},{"Player":"dave h","CommunityID":5,"Disconnectedness":0.2500630171,"AvgDisconnectedness":0.5246725369},{"Player":"gwido r","CommunityID":5,"Disconnectedness":0.2422133915,"AvgDisconnectedness":0.5246725369},{"Player":"ray a","CommunityID":5,"Disconnectedness":0.2413180913,"AvgDisconnectedness":0.5246725369},{"Player":"russ w","CommunityID":5,"Disconnectedness":0.1676888146,"AvgDisconnectedness":0.5246725369},{"Player":"bob g","CommunityID":5,"Disconnectedness":0.1667222826,"AvgDisconnectedness":0.5246725369},{"Player":"dave s","CommunityID":5,"Disconnectedness":0.1620678709,"AvgDisconnectedness":0.5246725369},{"Player":"chris m","CommunityID":5,"Disconnectedness":0.1387557232,"AvgDisconnectedness":0.5246725369},{"Player":"james s","CommunityID":5,"Disconnectedness":0.1379816606,"AvgDisconnectedness":0.5246725369},{"Player":"josh j","CommunityID":5,"Disconnectedness":0.1238299413,"AvgDisconnectedness":0.5246725369},{"Player":"dino ?","CommunityID":5,"Disconnectedness":0.1098227082,"AvgDisconnectedness":0.5246725369},{"Player":"jawad d","CommunityID":5,"Disconnectedness":0.1037093403,"AvgDisconnectedness":0.5246725369},{"Player":"gus h","CommunityID":5,"Disconnectedness":0.0769549369,"AvgDisconnectedness":0.5246725369},{"Player":"robert b","CommunityID":5,"Disconnectedness":0.0703801866,"AvgDisconnectedness":0.5246725369},{"Player":"eric h","CommunityID":5,"Disconnectedness":0.0665603814,"AvgDisconnectedness":0.5246725369},{"Player":"bill e","CommunityID":5,"Disconnectedness":0.0187578733,"AvgDisconnectedness":0.5246725369},{"Player":"johnathan h","CommunityID":5,"Disconnectedness":0.0176518263,"AvgDisconnectedness":0.5246725369},{"Player":"wyatt s","CommunityID":5,"Disconnectedness":0.0131348574,"AvgDisconnectedness":0.5246725369},{"Player":"caleb g","CommunityID":5,"Disconnectedness":0.0072950538,"AvgDisconnectedness":0.5246725369},{"Player":"ben d","CommunityID":5,"Disconnectedness":0.005100357,"AvgDisconnectedness":0.5246725369},{"Player":"cindy r","CommunityID":5,"Disconnectedness":0.0018976596,"AvgDisconnectedness":0.5246725369},{"Player":"troy r","CommunityID":5,"Disconnectedness":0.0009394223,"AvgDisconnectedness":0.5246725369},{"Player":"kasi ?","CommunityID":3,"Disconnectedness":1.0,"AvgDisconnectedness":0.4622948601},{"Player":"ricky ?","CommunityID":3,"Disconnectedness":0.9933523812,"AvgDisconnectedness":0.4622948601},{"Player":"shawn k","CommunityID":3,"Disconnectedness":0.9933523812,"AvgDisconnectedness":0.4622948601},{"Player":"orlando ?","CommunityID":3,"Disconnectedness":0.9918711012,"AvgDisconnectedness":0.4622948601},{"Player":"aj ?","CommunityID":3,"Disconnectedness":0.9915675484,"AvgDisconnectedness":0.4622948601},{"Player":"aj r","CommunityID":3,"Disconnectedness":0.9811370754,"AvgDisconnectedness":0.4622948601},{"Player":"joe f","CommunityID":3,"Disconnectedness":0.9793759056,"AvgDisconnectedness":0.4622948601},{"Player":"britt t","CommunityID":3,"Disconnectedness":0.9775558585,"AvgDisconnectedness":0.4622948601},{"Player":"sam c","CommunityID":3,"Disconnectedness":0.9677427643,"AvgDisconnectedness":0.4622948601},{"Player":"lisa ?","CommunityID":3,"Disconnectedness":0.9676296982,"AvgDisconnectedness":0.4622948601},{"Player":"justyn s","CommunityID":3,"Disconnectedness":0.9664586131,"AvgDisconnectedness":0.4622948601},{"Player":"ryker j","CommunityID":3,"Disconnectedness":0.9664586131,"AvgDisconnectedness":0.4622948601},{"Player":"luke s","CommunityID":3,"Disconnectedness":0.5006876882,"AvgDisconnectedness":0.4622948601},{"Player":"dave v","CommunityID":3,"Disconnectedness":0.4792288793,"AvgDisconnectedness":0.4622948601},{"Player":"cole g","CommunityID":3,"Disconnectedness":0.2705879436,"AvgDisconnectedness":0.4622948601},{"Player":"chris g","CommunityID":3,"Disconnectedness":0.2298248967,"AvgDisconnectedness":0.4622948601},{"Player":"igor m","CommunityID":3,"Disconnectedness":0.2209931969,"AvgDisconnectedness":0.4622948601},{"Player":"wendell e","CommunityID":3,"Disconnectedness":0.1639855165,"AvgDisconnectedness":0.4622948601},{"Player":"steven u","CommunityID":3,"Disconnectedness":0.1090406619,"AvgDisconnectedness":0.4622948601},{"Player":"tim c","CommunityID":3,"Disconnectedness":0.096076342,"AvgDisconnectedness":0.4622948601},{"Player":"dawson z","CommunityID":3,"Disconnectedness":0.0715859973,"AvgDisconnectedness":0.4622948601},{"Player":"john l","CommunityID":3,"Disconnectedness":0.0680788462,"AvgDisconnectedness":0.4622948601},{"Player":"paul u","CommunityID":3,"Disconnectedness":0.0564418414,"AvgDisconnectedness":0.4622948601},{"Player":"adam u","CommunityID":3,"Disconnectedness":0.0544327989,"AvgDisconnectedness":0.4622948601},{"Player":"kevin m","CommunityID":3,"Disconnectedness":0.0448858029,"AvgDisconnectedness":0.4622948601},{"Player":"zach f","CommunityID":3,"Disconnectedness":0.0362209704,"AvgDisconnectedness":0.4622948601},{"Player":"damian a","CommunityID":3,"Disconnectedness":0.036039837,"AvgDisconnectedness":0.4622948601},{"Player":"jarrett f","CommunityID":3,"Disconnectedness":0.0353531121,"AvgDisconnectedness":0.4622948601},{"Player":"mike l","CommunityID":3,"Disconnectedness":0.0276662889,"AvgDisconnectedness":0.4622948601},{"Player":"roger w","CommunityID":3,"Disconnectedness":0.026831225,"AvgDisconnectedness":0.4622948601},{"Player":"charlie t","CommunityID":3,"Disconnectedness":0.026676877,"AvgDisconnectedness":0.4622948601},{"Player":"alec r","CommunityID":2,"Disconnectedness":0.9777960789,"AvgDisconnectedness":0.4445714587},{"Player":"tom r","CommunityID":2,"Disconnectedness":0.9770589954,"AvgDisconnectedness":0.4445714587},{"Player":"sharky mark","CommunityID":2,"Disconnectedness":0.9769658488,"AvgDisconnectedness":0.4445714587},{"Player":"andrea ?","CommunityID":2,"Disconnectedness":0.9750224317,"AvgDisconnectedness":0.4445714587},{"Player":"alicia ?","CommunityID":2,"Disconnectedness":0.9727121381,"AvgDisconnectedness":0.4445714587},{"Player":"steve r","CommunityID":2,"Disconnectedness":0.9713368188,"AvgDisconnectedness":0.4445714587},{"Player":"mario g","CommunityID":2,"Disconnectedness":0.9700515007,"AvgDisconnectedness":0.4445714587},{"Player":"eric m","CommunityID":2,"Disconnectedness":0.9683570664,"AvgDisconnectedness":0.4445714587},{"Player":"gary m","CommunityID":2,"Disconnectedness":0.9683570664,"AvgDisconnectedness":0.4445714587},{"Player":"art m","CommunityID":2,"Disconnectedness":0.9631417582,"AvgDisconnectedness":0.4445714587},{"Player":"big bob h","CommunityID":2,"Disconnectedness":0.9631417582,"AvgDisconnectedness":0.4445714587},{"Player":"seamus w","CommunityID":2,"Disconnectedness":0.9631417582,"AvgDisconnectedness":0.4445714587},{"Player":"vern","CommunityID":2,"Disconnectedness":0.9631417582,"AvgDisconnectedness":0.4445714587},{"Player":"scott ?","CommunityID":2,"Disconnectedness":0.489172156,"AvgDisconnectedness":0.4445714587},{"Player":"mickey ?","CommunityID":2,"Disconnectedness":0.4863019626,"AvgDisconnectedness":0.4445714587},{"Player":"gene g","CommunityID":2,"Disconnectedness":0.481379148,"AvgDisconnectedness":0.4445714587},{"Player":"arsen o","CommunityID":2,"Disconnectedness":0.4812759616,"AvgDisconnectedness":0.4445714587},{"Player":"jason s","CommunityID":2,"Disconnectedness":0.4786563019,"AvgDisconnectedness":0.4445714587},{"Player":"dallas h","CommunityID":2,"Disconnectedness":0.3253481972,"AvgDisconnectedness":0.4445714587},{"Player":"david h","CommunityID":2,"Disconnectedness":0.3252489777,"AvgDisconnectedness":0.4445714587},{"Player":"hilda h","CommunityID":2,"Disconnectedness":0.3252489777,"AvgDisconnectedness":0.4445714587},{"Player":"dr z","CommunityID":2,"Disconnectedness":0.3170606541,"AvgDisconnectedness":0.4445714587},{"Player":"bree s","CommunityID":2,"Disconnectedness":0.2436255722,"AvgDisconnectedness":0.4445714587},{"Player":"alex a","CommunityID":2,"Disconnectedness":0.1930352539,"AvgDisconnectedness":0.4445714587},{"Player":"drew ?","CommunityID":2,"Disconnectedness":0.1388751578,"AvgDisconnectedness":0.4445714587},{"Player":"mike e","CommunityID":2,"Disconnectedness":0.0641903795,"AvgDisconnectedness":0.4445714587},{"Player":"ben l","CommunityID":2,"Disconnectedness":0.0591790669,"AvgDisconnectedness":0.4445714587},{"Player":"marty c","CommunityID":2,"Disconnectedness":0.0499825162,"AvgDisconnectedness":0.4445714587},{"Player":"kay l","CommunityID":2,"Disconnectedness":0.0461167236,"AvgDisconnectedness":0.4445714587},{"Player":"will l","CommunityID":2,"Disconnectedness":0.0437778124,"AvgDisconnectedness":0.4445714587},{"Player":"milan m","CommunityID":2,"Disconnectedness":0.0365731099,"AvgDisconnectedness":0.4445714587},{"Player":"dmitry l","CommunityID":2,"Disconnectedness":0.0348864472,"AvgDisconnectedness":0.4445714587},{"Player":"marina d","CommunityID":2,"Disconnectedness":0.0283645431,"AvgDisconnectedness":0.4445714587},{"Player":"john e","CommunityID":2,"Disconnectedness":0.0249643106,"AvgDisconnectedness":0.4445714587},{"Player":"gene d","CommunityID":2,"Disconnectedness":0.0243512709,"AvgDisconnectedness":0.4445714587},{"Player":"carol f","CommunityID":2,"Disconnectedness":0.0239587706,"AvgDisconnectedness":0.4445714587},{"Player":"lori h","CommunityID":2,"Disconnectedness":0.0051518451,"AvgDisconnectedness":0.4445714587},{"Player":"greg h","CommunityID":2,"Disconnectedness":0.0013367944,"AvgDisconnectedness":0.4445714587},{"Player":"rob h","CommunityID":2,"Disconnectedness":0.0,"AvgDisconnectedness":0.4445714587},{"Player":"viktor v","CommunityID":4,"Disconnectedness":0.9790618007,"AvgDisconnectedness":0.4286218635},{"Player":"mikayla m","CommunityID":4,"Disconnectedness":0.9755055896,"AvgDisconnectedness":0.4286218635},{"Player":"purple lotus","CommunityID":4,"Disconnectedness":0.9727452426,"AvgDisconnectedness":0.4286218635},{"Player":"william m","CommunityID":4,"Disconnectedness":0.9727452426,"AvgDisconnectedness":0.4286218635},{"Player":"viktor ?","CommunityID":4,"Disconnectedness":0.9718787244,"AvgDisconnectedness":0.4286218635},{"Player":"brandon p","CommunityID":4,"Disconnectedness":0.9718287376,"AvgDisconnectedness":0.4286218635},{"Player":"corey t","CommunityID":4,"Disconnectedness":0.9710024485,"AvgDisconnectedness":0.4286218635},{"Player":"jennifer g","CommunityID":4,"Disconnectedness":0.9704851832,"AvgDisconnectedness":0.4286218635},{"Player":"rachel b","CommunityID":4,"Disconnectedness":0.9691382111,"AvgDisconnectedness":0.4286218635},{"Player":"barbara m","CommunityID":4,"Disconnectedness":0.9666699771,"AvgDisconnectedness":0.4286218635},{"Player":"liam m","CommunityID":4,"Disconnectedness":0.9666699771,"AvgDisconnectedness":0.4286218635},{"Player":"brennan r","CommunityID":4,"Disconnectedness":0.9599943988,"AvgDisconnectedness":0.4286218635},{"Player":"ian h","CommunityID":4,"Disconnectedness":0.9599943988,"AvgDisconnectedness":0.4286218635},{"Player":"mike p","CommunityID":4,"Disconnectedness":0.9599943988,"AvgDisconnectedness":0.4286218635},{"Player":"tyler r","CommunityID":4,"Disconnectedness":0.5344532746,"AvgDisconnectedness":0.4286218635},{"Player":"carl b","CommunityID":4,"Disconnectedness":0.5216128344,"AvgDisconnectedness":0.4286218635},{"Player":"veronica m","CommunityID":4,"Disconnectedness":0.4886172082,"AvgDisconnectedness":0.4286218635},{"Player":"connor k","CommunityID":4,"Disconnectedness":0.4884288453,"AvgDisconnectedness":0.4286218635},{"Player":"jaxon a","CommunityID":4,"Disconnectedness":0.4858273953,"AvgDisconnectedness":0.4286218635},{"Player":"quinn mcclure","CommunityID":4,"Disconnectedness":0.4851340338,"AvgDisconnectedness":0.4286218635},{"Player":"john n","CommunityID":4,"Disconnectedness":0.3232591249,"AvgDisconnectedness":0.4286218635},{"Player":"aaron c","CommunityID":4,"Disconnectedness":0.3228003898,"AvgDisconnectedness":0.4286218635},{"Player":"alex c","CommunityID":4,"Disconnectedness":0.3223243228,"AvgDisconnectedness":0.4286218635},{"Player":"pat m","CommunityID":4,"Disconnectedness":0.3177314958,"AvgDisconnectedness":0.4286218635},{"Player":"john h","CommunityID":4,"Disconnectedness":0.3157653158,"AvgDisconnectedness":0.4286218635},{"Player":"isaiah j","CommunityID":4,"Disconnectedness":0.2432539329,"AvgDisconnectedness":0.4286218635},{"Player":"matthew o","CommunityID":4,"Disconnectedness":0.2427023256,"AvgDisconnectedness":0.4286218635},{"Player":"matthew s","CommunityID":4,"Disconnectedness":0.1969806146,"AvgDisconnectedness":0.4286218635},{"Player":"robyn h","CommunityID":4,"Disconnectedness":0.1958269887,"AvgDisconnectedness":0.4286218635},{"Player":"marcus p","CommunityID":4,"Disconnectedness":0.187741359,"AvgDisconnectedness":0.4286218635},{"Player":"will g","CommunityID":4,"Disconnectedness":0.163265679,"AvgDisconnectedness":0.4286218635},{"Player":"jason b","CommunityID":4,"Disconnectedness":0.1532442803,"AvgDisconnectedness":0.4286218635},{"Player":"alex k","CommunityID":4,"Disconnectedness":0.143728486,"AvgDisconnectedness":0.4286218635},{"Player":"harry h","CommunityID":4,"Disconnectedness":0.1268033344,"AvgDisconnectedness":0.4286218635},{"Player":"mike m","CommunityID":4,"Disconnectedness":0.109726081,"AvgDisconnectedness":0.4286218635},{"Player":"jordan h","CommunityID":4,"Disconnectedness":0.0921979593,"AvgDisconnectedness":0.4286218635},{"Player":"mike pierce","CommunityID":4,"Disconnectedness":0.0866380026,"AvgDisconnectedness":0.4286218635},{"Player":"rishav r","CommunityID":4,"Disconnectedness":0.0694440978,"AvgDisconnectedness":0.4286218635},{"Player":"tekoya c","CommunityID":4,"Disconnectedness":0.0629033152,"AvgDisconnectedness":0.4286218635},{"Player":"grace r","CommunityID":4,"Disconnectedness":0.059673526,"AvgDisconnectedness":0.4286218635},{"Player":"sean g","CommunityID":4,"Disconnectedness":0.0506443673,"AvgDisconnectedness":0.4286218635},{"Player":"ahmad b","CommunityID":4,"Disconnectedness":0.0487593373,"AvgDisconnectedness":0.4286218635},{"Player":"aj l","CommunityID":4,"Disconnectedness":0.0472436884,"AvgDisconnectedness":0.4286218635},{"Player":"mason g","CommunityID":4,"Disconnectedness":0.0373197968,"AvgDisconnectedness":0.4286218635},{"Player":"geralyn g","CommunityID":4,"Disconnectedness":0.0324688641,"AvgDisconnectedness":0.4286218635},{"Player":"greg s","CommunityID":4,"Disconnectedness":0.0255265471,"AvgDisconnectedness":0.4286218635},{"Player":"amar n","CommunityID":4,"Disconnectedness":0.016063194,"AvgDisconnectedness":0.4286218635},{"Player":"john f","CommunityID":4,"Disconnectedness":0.0080250966,"AvgDisconnectedness":0.4286218635},{"Player":"brian p","CommunityID":1,"Disconnectedness":0.9803054541,"AvgDisconnectedness":0.4009940282},{"Player":"mike legg","CommunityID":1,"Disconnectedness":0.9775552165,"AvgDisconnectedness":0.4009940282},{"Player":"dale p","CommunityID":1,"Disconnectedness":0.9774268067,"AvgDisconnectedness":0.4009940282},{"Player":"joe c","CommunityID":1,"Disconnectedness":0.9774268067,"AvgDisconnectedness":0.4009940282},{"Player":"ben n","CommunityID":1,"Disconnectedness":0.9750096375,"AvgDisconnectedness":0.4009940282},{"Player":"oz b","CommunityID":1,"Disconnectedness":0.9743582647,"AvgDisconnectedness":0.4009940282},{"Player":"mike s","CommunityID":1,"Disconnectedness":0.9733993223,"AvgDisconnectedness":0.4009940282},{"Player":"james p","CommunityID":1,"Disconnectedness":0.9720327842,"AvgDisconnectedness":0.4009940282},{"Player":"enea ?","CommunityID":1,"Disconnectedness":0.9718905797,"AvgDisconnectedness":0.4009940282},{"Player":"jerome k","CommunityID":1,"Disconnectedness":0.9690953054,"AvgDisconnectedness":0.4009940282},{"Player":"noel l","CommunityID":1,"Disconnectedness":0.9673659348,"AvgDisconnectedness":0.4009940282},{"Player":"trevyn f","CommunityID":1,"Disconnectedness":0.9672234562,"AvgDisconnectedness":0.4009940282},{"Player":"adrian c","CommunityID":1,"Disconnectedness":0.9670890964,"AvgDisconnectedness":0.4009940282},{"Player":"brian h","CommunityID":1,"Disconnectedness":0.9668405621,"AvgDisconnectedness":0.4009940282},{"Player":"joe r","CommunityID":1,"Disconnectedness":0.9668405621,"AvgDisconnectedness":0.4009940282},{"Player":"kevin h","CommunityID":1,"Disconnectedness":0.9668103661,"AvgDisconnectedness":0.4009940282},{"Player":"hunter ?","CommunityID":1,"Disconnectedness":0.9667510409,"AvgDisconnectedness":0.4009940282},{"Player":"donovan","CommunityID":1,"Disconnectedness":0.966087603,"AvgDisconnectedness":0.4009940282},{"Player":"michelle g","CommunityID":1,"Disconnectedness":0.9658612579,"AvgDisconnectedness":0.4009940282},{"Player":"carl ?","CommunityID":1,"Disconnectedness":0.9637554226,"AvgDisconnectedness":0.4009940282},{"Player":"emily ?","CommunityID":1,"Disconnectedness":0.9637554226,"AvgDisconnectedness":0.4009940282},{"Player":"katie ?","CommunityID":1,"Disconnectedness":0.9637554226,"AvgDisconnectedness":0.4009940282},{"Player":"lisa h","CommunityID":1,"Disconnectedness":0.9631392529,"AvgDisconnectedness":0.4009940282},{"Player":"spencer l","CommunityID":1,"Disconnectedness":0.4936703978,"AvgDisconnectedness":0.4009940282},{"Player":"jennifer c","CommunityID":1,"Disconnectedness":0.4923360672,"AvgDisconnectedness":0.4009940282},{"Player":"brandon i","CommunityID":1,"Disconnectedness":0.4902799382,"AvgDisconnectedness":0.4009940282},{"Player":"brita w","CommunityID":1,"Disconnectedness":0.4890286541,"AvgDisconnectedness":0.4009940282},{"Player":"gary g","CommunityID":1,"Disconnectedness":0.4876783872,"AvgDisconnectedness":0.4009940282},{"Player":"jalani d","CommunityID":1,"Disconnectedness":0.4838899413,"AvgDisconnectedness":0.4009940282},{"Player":"steve j","CommunityID":1,"Disconnectedness":0.4803432282,"AvgDisconnectedness":0.4009940282},{"Player":"ray l","CommunityID":1,"Disconnectedness":0.4785016027,"AvgDisconnectedness":0.4009940282},{"Player":"brandon h","CommunityID":1,"Disconnectedness":0.4777327278,"AvgDisconnectedness":0.4009940282},{"Player":"mercedez m","CommunityID":1,"Disconnectedness":0.4766456132,"AvgDisconnectedness":0.4009940282},{"Player":"nathan l","CommunityID":1,"Disconnectedness":0.3293673487,"AvgDisconnectedness":0.4009940282},{"Player":"ellie f","CommunityID":1,"Disconnectedness":0.3234536596,"AvgDisconnectedness":0.4009940282},{"Player":"dave j","CommunityID":1,"Disconnectedness":0.319480772,"AvgDisconnectedness":0.4009940282},{"Player":"veronica c","CommunityID":1,"Disconnectedness":0.3194284936,"AvgDisconnectedness":0.4009940282},{"Player":"david kong","CommunityID":1,"Disconnectedness":0.3174094103,"AvgDisconnectedness":0.4009940282},{"Player":"nicole l","CommunityID":1,"Disconnectedness":0.3174094103,"AvgDisconnectedness":0.4009940282},{"Player":"amar","CommunityID":1,"Disconnectedness":0.3148611066,"AvgDisconnectedness":0.4009940282},{"Player":"tony s","CommunityID":1,"Disconnectedness":0.314121752,"AvgDisconnectedness":0.4009940282},{"Player":"jared c","CommunityID":1,"Disconnectedness":0.2473068453,"AvgDisconnectedness":0.4009940282},{"Player":"lisa v","CommunityID":1,"Disconnectedness":0.2459568981,"AvgDisconnectedness":0.4009940282},{"Player":"gavin ?","CommunityID":1,"Disconnectedness":0.2450993386,"AvgDisconnectedness":0.4009940282},{"Player":"tom z","CommunityID":1,"Disconnectedness":0.2353307018,"AvgDisconnectedness":0.4009940282},{"Player":"ken l","CommunityID":1,"Disconnectedness":0.2017435385,"AvgDisconnectedness":0.4009940282},{"Player":"marcus ?","CommunityID":1,"Disconnectedness":0.1958494585,"AvgDisconnectedness":0.4009940282},{"Player":"dennis f","CommunityID":1,"Disconnectedness":0.192018655,"AvgDisconnectedness":0.4009940282},{"Player":"kris k","CommunityID":1,"Disconnectedness":0.1722516646,"AvgDisconnectedness":0.4009940282},{"Player":"steve b","CommunityID":1,"Disconnectedness":0.1452801575,"AvgDisconnectedness":0.4009940282},{"Player":"bryan o","CommunityID":1,"Disconnectedness":0.1446475002,"AvgDisconnectedness":0.4009940282},{"Player":"wayne c","CommunityID":1,"Disconnectedness":0.1424398634,"AvgDisconnectedness":0.4009940282},{"Player":"ano a","CommunityID":1,"Disconnectedness":0.1298930334,"AvgDisconnectedness":0.4009940282},{"Player":"tony smith","CommunityID":1,"Disconnectedness":0.1260074699,"AvgDisconnectedness":0.4009940282},{"Player":"tom k","CommunityID":1,"Disconnectedness":0.0979812915,"AvgDisconnectedness":0.4009940282},{"Player":"eric s","CommunityID":1,"Disconnectedness":0.0809108693,"AvgDisconnectedness":0.4009940282},{"Player":"jeremy k","CommunityID":1,"Disconnectedness":0.0801641785,"AvgDisconnectedness":0.4009940282},{"Player":"steph e","CommunityID":1,"Disconnectedness":0.0669118043,"AvgDisconnectedness":0.4009940282},{"Player":"evan d","CommunityID":1,"Disconnectedness":0.0593656964,"AvgDisconnectedness":0.4009940282},{"Player":"tony spenser","CommunityID":1,"Disconnectedness":0.0584777566,"AvgDisconnectedness":0.4009940282},{"Player":"lyle g","CommunityID":1,"Disconnectedness":0.0528187775,"AvgDisconnectedness":0.4009940282},{"Player":"john b","CommunityID":1,"Disconnectedness":0.0500110986,"AvgDisconnectedness":0.4009940282},{"Player":"paul p","CommunityID":1,"Disconnectedness":0.047960783,"AvgDisconnectedness":0.4009940282},{"Player":"rick r","CommunityID":1,"Disconnectedness":0.0474875301,"AvgDisconnectedness":0.4009940282},{"Player":"paul s","CommunityID":1,"Disconnectedness":0.0431404697,"AvgDisconnectedness":0.4009940282},{"Player":"mike t","CommunityID":1,"Disconnectedness":0.0423321294,"AvgDisconnectedness":0.4009940282},{"Player":"patty t","CommunityID":1,"Disconnectedness":0.0423321294,"AvgDisconnectedness":0.4009940282},{"Player":"katy v","CommunityID":1,"Disconnectedness":0.0419107578,"AvgDisconnectedness":0.4009940282},{"Player":"kevin b","CommunityID":1,"Disconnectedness":0.0395674535,"AvgDisconnectedness":0.4009940282},{"Player":"jaye s","CommunityID":1,"Disconnectedness":0.0393665026,"AvgDisconnectedness":0.4009940282},{"Player":"dave b","CommunityID":1,"Disconnectedness":0.0381150638,"AvgDisconnectedness":0.4009940282},{"Player":"richard m","CommunityID":1,"Disconnectedness":0.031854157,"AvgDisconnectedness":0.4009940282},{"Player":"jason h","CommunityID":1,"Disconnectedness":0.0263721531,"AvgDisconnectedness":0.4009940282},{"Player":"matt p","CommunityID":1,"Disconnectedness":0.0258218925,"AvgDisconnectedness":0.4009940282},{"Player":"deathnote l","CommunityID":1,"Disconnectedness":0.0244063916,"AvgDisconnectedness":0.4009940282},{"Player":"rieley p","CommunityID":1,"Disconnectedness":0.0195534317,"AvgDisconnectedness":0.4009940282},{"Player":"bobby c","CommunityID":1,"Disconnectedness":0.0189493624,"AvgDisconnectedness":0.4009940282},{"Player":"tony sr","CommunityID":1,"Disconnectedness":0.0175335224,"AvgDisconnectedness":0.4009940282},{"Player":"evan j","CommunityID":1,"Disconnectedness":0.0174567349,"AvgDisconnectedness":0.4009940282},{"Player":"carlee j","CommunityID":1,"Disconnectedness":0.014411513,"AvgDisconnectedness":0.4009940282},{"Player":"bartman p","CommunityID":1,"Disconnectedness":0.0095531257,"AvgDisconnectedness":0.4009940282},{"Player":"paul cb","CommunityID":1,"Disconnectedness":0.0077914636,"AvgDisconnectedness":0.4009940282},{"Player":"bonnie l","CommunityID":1,"Disconnectedness":0.0067070855,"AvgDisconnectedness":0.4009940282},{"Player":"james a","CommunityID":0,"Disconnectedness":0.9707816609,"AvgDisconnectedness":0.3274107215},{"Player":"angelica g","CommunityID":0,"Disconnectedness":0.9698253034,"AvgDisconnectedness":0.3274107215},{"Player":"vikrant punj","CommunityID":0,"Disconnectedness":0.9689774487,"AvgDisconnectedness":0.3274107215},{"Player":"johnny s","CommunityID":0,"Disconnectedness":0.9661579774,"AvgDisconnectedness":0.3274107215},{"Player":"wesley k","CommunityID":0,"Disconnectedness":0.9661579774,"AvgDisconnectedness":0.3274107215},{"Player":"reese r","CommunityID":0,"Disconnectedness":0.9637451511,"AvgDisconnectedness":0.3274107215},{"Player":"joey ?","CommunityID":0,"Disconnectedness":0.9636002262,"AvgDisconnectedness":0.3274107215},{"Player":"misebah n","CommunityID":0,"Disconnectedness":0.9627239584,"AvgDisconnectedness":0.3274107215},{"Player":"nick d","CommunityID":0,"Disconnectedness":0.9627239584,"AvgDisconnectedness":0.3274107215},{"Player":"lupillo r","CommunityID":0,"Disconnectedness":0.4837788196,"AvgDisconnectedness":0.3274107215},{"Player":"brian j","CommunityID":0,"Disconnectedness":0.4834211035,"AvgDisconnectedness":0.3274107215},{"Player":"tony jr","CommunityID":0,"Disconnectedness":0.4824205363,"AvgDisconnectedness":0.3274107215},{"Player":"alex w","CommunityID":0,"Disconnectedness":0.4768021501,"AvgDisconnectedness":0.3274107215},{"Player":"carter ?","CommunityID":0,"Disconnectedness":0.4768021501,"AvgDisconnectedness":0.3274107215},{"Player":"rico c","CommunityID":0,"Disconnectedness":0.3195841547,"AvgDisconnectedness":0.3274107215},{"Player":"domanic a","CommunityID":0,"Disconnectedness":0.3194834251,"AvgDisconnectedness":0.3274107215},{"Player":"floyd t","CommunityID":0,"Disconnectedness":0.2575387758,"AvgDisconnectedness":0.3274107215},{"Player":"joaquin m","CommunityID":0,"Disconnectedness":0.2382571976,"AvgDisconnectedness":0.3274107215},{"Player":"netty u","CommunityID":0,"Disconnectedness":0.1947966614,"AvgDisconnectedness":0.3274107215},{"Player":"darnell w","CommunityID":0,"Disconnectedness":0.1699657169,"AvgDisconnectedness":0.3274107215},{"Player":"jack d","CommunityID":0,"Disconnectedness":0.1389106875,"AvgDisconnectedness":0.3274107215},{"Player":"tracy s","CommunityID":0,"Disconnectedness":0.1382108525,"AvgDisconnectedness":0.3274107215},{"Player":"joe irish","CommunityID":0,"Disconnectedness":0.0955738868,"AvgDisconnectedness":0.3274107215},{"Player":"colton r","CommunityID":0,"Disconnectedness":0.0853799275,"AvgDisconnectedness":0.3274107215},{"Player":"clayton a","CommunityID":0,"Disconnectedness":0.0853237609,"AvgDisconnectedness":0.3274107215},{"Player":"mo m","CommunityID":0,"Disconnectedness":0.0719878966,"AvgDisconnectedness":0.3274107215},{"Player":"zach c","CommunityID":0,"Disconnectedness":0.0691736624,"AvgDisconnectedness":0.3274107215},{"Player":"john s","CommunityID":0,"Disconnectedness":0.0575317657,"AvgDisconnectedness":0.3274107215},{"Player":"sandy v","CommunityID":0,"Disconnectedness":0.0567187681,"AvgDisconnectedness":0.3274107215},{"Player":"mellisa h","CommunityID":0,"Disconnectedness":0.0455898323,"AvgDisconnectedness":0.3274107215},{"Player":"cristiana l","CommunityID":0,"Disconnectedness":0.0395087543,"AvgDisconnectedness":0.3274107215},{"Player":"brandon c","CommunityID":0,"Disconnectedness":0.0390651068,"AvgDisconnectedness":0.3274107215},{"Player":"adam m","CommunityID":0,"Disconnectedness":0.0332791639,"AvgDisconnectedness":0.3274107215},{"Player":"mercedes m","CommunityID":0,"Disconnectedness":0.0319619753,"AvgDisconnectedness":0.3274107215},{"Player":"devon t","CommunityID":0,"Disconnectedness":0.0304467917,"AvgDisconnectedness":0.3274107215},{"Player":"donovan b","CommunityID":0,"Disconnectedness":0.0294067446,"AvgDisconnectedness":0.3274107215},{"Player":"nico a","CommunityID":0,"Disconnectedness":0.0288824951,"AvgDisconnectedness":0.3274107215},{"Player":"miguel q","CommunityID":0,"Disconnectedness":0.0264308455,"AvgDisconnectedness":0.3274107215},{"Player":"steel neil","CommunityID":0,"Disconnectedness":0.0221529592,"AvgDisconnectedness":0.3274107215},{"Player":"jeremiah td","CommunityID":0,"Disconnectedness":0.0186818656,"AvgDisconnectedness":0.3274107215},{"Player":"bob r","CommunityID":0,"Disconnectedness":0.0079394805,"AvgDisconnectedness":0.3274107215},{"Player":"pyerre l","CommunityID":0,"Disconnectedness":0.0015487288,"AvgDisconnectedness":0.3274107215}]