[{"Player":"matt g","CommunityID":1,"Disconnectedness":0.982536894,"AvgDisconnectedness":0.5946170464},{"Player":"john k","CommunityID":1,"Disconnectedness":0.9771645327,"AvgDisconnectedness":0.5946170464},{"Player":"brenda n","CommunityID":1,"Disconnectedness":0.9768565116,"AvgDisconnectedness":0.5946170464},{"Player":"chris w","CommunityID":1,"Disconnectedness":0.9768565116,"AvgDisconnectedness":0.5946170464},{"Player":"dan h","CommunityID":1,"Disconnectedness":0.9768565116,"AvgDisconnectedness":0.5946170464},{"Player":"ray b","CommunityID":1,"Disconnectedness":0.9768565116,"AvgDisconnectedness":0.5946170464},{"Player":"alex e","CommunityID":1,"Disconnectedness":0.9767161006,"AvgDisconnectedness":0.5946170464},{"Player":"yeng t","CommunityID":1,"Disconnectedness":0.9767161006,"AvgDisconnectedness":0.5946170464},{"Player":"fritz p","CommunityID":1,"Disconnectedness":0.9761959291,"AvgDisconnectedness":0.5946170464},{"Player":"josh v","CommunityID":1,"Disconnectedness":0.9761871723,"AvgDisconnectedness":0.5946170464},{"Player":"becca r","CommunityID":1,"Disconnectedness":0.9761188811,"AvgDisconnectedness":0.5946170464},{"Player":"matt petermann","CommunityID":1,"Disconnectedness":0.9761188811,"AvgDisconnectedness":0.5946170464},{"Player":"john p","CommunityID":1,"Disconnectedness":0.9753251035,"AvgDisconnectedness":0.5946170464},{"Player":"anthony m","CommunityID":1,"Disconnectedness":0.9749917026,"AvgDisconnectedness":0.5946170464},{"Player":"mario g","CommunityID":1,"Disconnectedness":0.9747201981,"AvgDisconnectedness":0.5946170464},{"Player":"ken h","CommunityID":1,"Disconnectedness":0.9732501977,"AvgDisconnectedness":0.5946170464},{"Player":"tara m","CommunityID":1,"Disconnectedness":0.9732501977,"AvgDisconnectedness":0.5946170464},{"Player":"vicki m","CommunityID":1,"Disconnectedness":0.9732501977,"AvgDisconnectedness":0.5946170464},{"Player":"oz dog","CommunityID":1,"Disconnectedness":0.9731548032,"AvgDisconnectedness":0.5946170464},{"Player":"tim n","CommunityID":1,"Disconnectedness":0.9731548032,"AvgDisconnectedness":0.5946170464},{"Player":"justyn s","CommunityID":1,"Disconnectedness":0.9721208952,"AvgDisconnectedness":0.5946170464},{"Player":"ryker j","CommunityID":1,"Disconnectedness":0.9721208952,"AvgDisconnectedness":0.5946170464},{"Player":"joey w","CommunityID":1,"Disconnectedness":0.9718767611,"AvgDisconnectedness":0.5946170464},{"Player":"emerson m","CommunityID":1,"Disconnectedness":0.9694402099,"AvgDisconnectedness":0.5946170464},{"Player":"will t","CommunityID":1,"Disconnectedness":0.9694402099,"AvgDisconnectedness":0.5946170464},{"Player":"adam w","CommunityID":1,"Disconnectedness":0.9618499256,"AvgDisconnectedness":0.5946170464},{"Player":"charlie p","CommunityID":1,"Disconnectedness":0.9618499256,"AvgDisconnectedness":0.5946170464},{"Player":"james k","CommunityID":1,"Disconnectedness":0.9618499256,"AvgDisconnectedness":0.5946170464},{"Player":"jeremy m","CommunityID":1,"Disconnectedness":0.9618499256,"AvgDisconnectedness":0.5946170464},{"Player":"walker w","CommunityID":1,"Disconnectedness":0.9618499256,"AvgDisconnectedness":0.5946170464},{"Player":"kayla h","CommunityID":1,"Disconnectedness":0.4933342651,"AvgDisconnectedness":0.5946170464},{"Player":"joe graham","CommunityID":1,"Disconnectedness":0.4915237679,"AvgDisconnectedness":0.5946170464},{"Player":"rob c","CommunityID":1,"Disconnectedness":0.488158813,"AvgDisconnectedness":0.5946170464},{"Player":"tim j","CommunityID":1,"Disconnectedness":0.4838320016,"AvgDisconnectedness":0.5946170464},{"Player":"gary n","CommunityID":1,"Disconnectedness":0.483621852,"AvgDisconnectedness":0.5946170464},{"Player":"dana b","CommunityID":1,"Disconnectedness":0.4830048391,"AvgDisconnectedness":0.5946170464},{"Player":"fred h","CommunityID":1,"Disconnectedness":0.4830048391,"AvgDisconnectedness":0.5946170464},{"Player":"dave v","CommunityID":1,"Disconnectedness":0.4824957301,"AvgDisconnectedness":0.5946170464},{"Player":"willie w","CommunityID":1,"Disconnectedness":0.3213680517,"AvgDisconnectedness":0.5946170464},{"Player":"dave h","CommunityID":1,"Disconnectedness":0.2513641504,"AvgDisconnectedness":0.5946170464},{"Player":"gwido r","CommunityID":1,"Disconnectedness":0.2430857217,"AvgDisconnectedness":0.5946170464},{"Player":"bryon p","CommunityID":1,"Disconnectedness":0.2403189605,"AvgDisconnectedness":0.5946170464},{"Player":"dino c","CommunityID":1,"Disconnectedness":0.2403189605,"AvgDisconnectedness":0.5946170464},{"Player":"ray a","CommunityID":1,"Disconnectedness":0.2393390356,"AvgDisconnectedness":0.5946170464},{"Player":"russ w","CommunityID":1,"Disconnectedness":0.1660793049,"AvgDisconnectedness":0.5946170464},{"Player":"dave s","CommunityID":1,"Disconnectedness":0.1625982167,"AvgDisconnectedness":0.5946170464},{"Player":"dino ?","CommunityID":1,"Disconnectedness":0.1410453545,"AvgDisconnectedness":0.5946170464},{"Player":"chris m","CommunityID":1,"Disconnectedness":0.1390600032,"AvgDisconnectedness":0.5946170464},{"Player":"james s","CommunityID":1,"Disconnectedness":0.1224202082,"AvgDisconnectedness":0.5946170464},{"Player":"josh j","CommunityID":1,"Disconnectedness":0.0900762198,"AvgDisconnectedness":0.5946170464},{"Player":"gus h","CommunityID":1,"Disconnectedness":0.0777908778,"AvgDisconnectedness":0.5946170464},{"Player":"robert b","CommunityID":1,"Disconnectedness":0.0704217924,"AvgDisconnectedness":0.5946170464},{"Player":"sandy v","CommunityID":1,"Disconnectedness":0.0570751131,"AvgDisconnectedness":0.5946170464},{"Player":"johnathan h","CommunityID":1,"Disconnectedness":0.0166621042,"AvgDisconnectedness":0.5946170464},{"Player":"bill e","CommunityID":1,"Disconnectedness":0.016441925,"AvgDisconnectedness":0.5946170464},{"Player":"caleb g","CommunityID":1,"Disconnectedness":0.0061186196,"AvgDisconnectedness":0.5946170464},{"Player":"ben d","CommunityID":1,"Disconnectedness":0.0026701165,"AvgDisconnectedness":0.5946170464},{"Player":"cindy r","CommunityID":1,"Disconnectedness":0.0013443179,"AvgDisconnectedness":0.5946170464},{"Player":"pyerre l","CommunityID":1,"Disconnectedness":0.0013150853,"AvgDisconnectedness":0.5946170464},{"Player":"troy r","CommunityID":1,"Disconnectedness":0.0006061938,"AvgDisconnectedness":0.5946170464},{"Player":"viktor v","CommunityID":3,"Disconnectedness":0.9841743462,"AvgDisconnectedness":0.4322082299},{"Player":"tenzen r","CommunityID":3,"Disconnectedness":0.9802594715,"AvgDisconnectedness":0.4322082299},{"Player":"william b","CommunityID":3,"Disconnectedness":0.9802594715,"AvgDisconnectedness":0.4322082299},{"Player":"mikayla m","CommunityID":3,"Disconnectedness":0.9791392996,"AvgDisconnectedness":0.4322082299},{"Player":"matt b","CommunityID":3,"Disconnectedness":0.9774535789,"AvgDisconnectedness":0.4322082299},{"Player":"purple lotus","CommunityID":3,"Disconnectedness":0.9767524727,"AvgDisconnectedness":0.4322082299},{"Player":"william m","CommunityID":3,"Disconnectedness":0.9767524727,"AvgDisconnectedness":0.4322082299},{"Player":"brandon p","CommunityID":3,"Disconnectedness":0.9760805751,"AvgDisconnectedness":0.4322082299},{"Player":"kenny z","CommunityID":3,"Disconnectedness":0.9758902293,"AvgDisconnectedness":0.4322082299},{"Player":"viktor ?","CommunityID":3,"Disconnectedness":0.9758660467,"AvgDisconnectedness":0.4322082299},{"Player":"jennifer g","CommunityID":3,"Disconnectedness":0.9757322528,"AvgDisconnectedness":0.4322082299},{"Player":"gary","CommunityID":3,"Disconnectedness":0.9753370128,"AvgDisconnectedness":0.4322082299},{"Player":"beckett c","CommunityID":3,"Disconnectedness":0.9738842623,"AvgDisconnectedness":0.4322082299},{"Player":"rachel b","CommunityID":3,"Disconnectedness":0.9736398568,"AvgDisconnectedness":0.4322082299},{"Player":"jake s","CommunityID":3,"Disconnectedness":0.9726819439,"AvgDisconnectedness":0.4322082299},{"Player":"brennan r","CommunityID":3,"Disconnectedness":0.9678269681,"AvgDisconnectedness":0.4322082299},{"Player":"ian h","CommunityID":3,"Disconnectedness":0.9678269681,"AvgDisconnectedness":0.4322082299},{"Player":"tyler r","CommunityID":3,"Disconnectedness":0.5261641037,"AvgDisconnectedness":0.4322082299},{"Player":"carl b","CommunityID":3,"Disconnectedness":0.522825714,"AvgDisconnectedness":0.4322082299},{"Player":"nate l","CommunityID":3,"Disconnectedness":0.5000776635,"AvgDisconnectedness":0.4322082299},{"Player":"connor k","CommunityID":3,"Disconnectedness":0.4903625682,"AvgDisconnectedness":0.4322082299},{"Player":"veronica m","CommunityID":3,"Disconnectedness":0.4894608308,"AvgDisconnectedness":0.4322082299},{"Player":"jaxon a","CommunityID":3,"Disconnectedness":0.4882800311,"AvgDisconnectedness":0.4322082299},{"Player":"quinn mcclure","CommunityID":3,"Disconnectedness":0.4865086948,"AvgDisconnectedness":0.4322082299},{"Player":"kaylah h","CommunityID":3,"Disconnectedness":0.3439589321,"AvgDisconnectedness":0.4322082299},{"Player":"mike p","CommunityID":3,"Disconnectedness":0.3356731365,"AvgDisconnectedness":0.4322082299},{"Player":"alex c","CommunityID":3,"Disconnectedness":0.3261421343,"AvgDisconnectedness":0.4322082299},{"Player":"isaiah j","CommunityID":3,"Disconnectedness":0.244261521,"AvgDisconnectedness":0.4322082299},{"Player":"matthew o","CommunityID":3,"Disconnectedness":0.2434116704,"AvgDisconnectedness":0.4322082299},{"Player":"john n","CommunityID":3,"Disconnectedness":0.239622725,"AvgDisconnectedness":0.4322082299},{"Player":"pat m","CommunityID":3,"Disconnectedness":0.2044659121,"AvgDisconnectedness":0.4322082299},{"Player":"ellie f","CommunityID":3,"Disconnectedness":0.2036994622,"AvgDisconnectedness":0.4322082299},{"Player":"matthew s","CommunityID":3,"Disconnectedness":0.1973849748,"AvgDisconnectedness":0.4322082299},{"Player":"barbara m","CommunityID":3,"Disconnectedness":0.1919237982,"AvgDisconnectedness":0.4322082299},{"Player":"liam m","CommunityID":3,"Disconnectedness":0.1919237982,"AvgDisconnectedness":0.4322082299},{"Player":"will g","CommunityID":3,"Disconnectedness":0.163744297,"AvgDisconnectedness":0.4322082299},{"Player":"john h","CommunityID":3,"Disconnectedness":0.1629256651,"AvgDisconnectedness":0.4322082299},{"Player":"marcus p","CommunityID":3,"Disconnectedness":0.1425281257,"AvgDisconnectedness":0.4322082299},{"Player":"jason b","CommunityID":3,"Disconnectedness":0.1286922047,"AvgDisconnectedness":0.4322082299},{"Player":"mike m","CommunityID":3,"Disconnectedness":0.1017111897,"AvgDisconnectedness":0.4322082299},{"Player":"harry h","CommunityID":3,"Disconnectedness":0.0908624863,"AvgDisconnectedness":0.4322082299},{"Player":"alex k","CommunityID":3,"Disconnectedness":0.0761434916,"AvgDisconnectedness":0.4322082299},{"Player":"mike pierce","CommunityID":3,"Disconnectedness":0.0690498052,"AvgDisconnectedness":0.4322082299},{"Player":"rishav r","CommunityID":3,"Disconnectedness":0.0638950521,"AvgDisconnectedness":0.4322082299},{"Player":"tekoya c","CommunityID":3,"Disconnectedness":0.053895403,"AvgDisconnectedness":0.4322082299},{"Player":"grace r","CommunityID":3,"Disconnectedness":0.0452464596,"AvgDisconnectedness":0.4322082299},{"Player":"sean g","CommunityID":3,"Disconnectedness":0.0426969916,"AvgDisconnectedness":0.4322082299},{"Player":"ahmad b","CommunityID":3,"Disconnectedness":0.041359204,"AvgDisconnectedness":0.4322082299},{"Player":"aj l","CommunityID":3,"Disconnectedness":0.0377837405,"AvgDisconnectedness":0.4322082299},{"Player":"cristiana l","CommunityID":3,"Disconnectedness":0.03698871,"AvgDisconnectedness":0.4322082299},{"Player":"mason g","CommunityID":3,"Disconnectedness":0.0325604079,"AvgDisconnectedness":0.4322082299},{"Player":"geralyn g","CommunityID":3,"Disconnectedness":0.0313846349,"AvgDisconnectedness":0.4322082299},{"Player":"greg s","CommunityID":3,"Disconnectedness":0.0245207556,"AvgDisconnectedness":0.4322082299},{"Player":"donovan b","CommunityID":3,"Disconnectedness":0.0232580723,"AvgDisconnectedness":0.4322082299},{"Player":"amar n","CommunityID":3,"Disconnectedness":0.0111079612,"AvgDisconnectedness":0.4322082299},{"Player":"john f","CommunityID":3,"Disconnectedness":0.0076013188,"AvgDisconnectedness":0.4322082299},{"Player":"alec r","CommunityID":4,"Disconnectedness":0.9819777617,"AvgDisconnectedness":0.4238054616},{"Player":"tom r","CommunityID":4,"Disconnectedness":0.981433324,"AvgDisconnectedness":0.4238054616},{"Player":"sharky mark","CommunityID":4,"Disconnectedness":0.9813762728,"AvgDisconnectedness":0.4238054616},{"Player":"andrea ?","CommunityID":4,"Disconnectedness":0.9796146855,"AvgDisconnectedness":0.4238054616},{"Player":"alicia ?","CommunityID":4,"Disconnectedness":0.9772268571,"AvgDisconnectedness":0.4238054616},{"Player":"steve r","CommunityID":4,"Disconnectedness":0.9755578155,"AvgDisconnectedness":0.4238054616},{"Player":"eric m","CommunityID":4,"Disconnectedness":0.9732619332,"AvgDisconnectedness":0.4238054616},{"Player":"gary m","CommunityID":4,"Disconnectedness":0.9732619332,"AvgDisconnectedness":0.4238054616},{"Player":"art m","CommunityID":4,"Disconnectedness":0.9691634393,"AvgDisconnectedness":0.4238054616},{"Player":"big bob h","CommunityID":4,"Disconnectedness":0.9691634393,"AvgDisconnectedness":0.4238054616},{"Player":"seamus w","CommunityID":4,"Disconnectedness":0.9691634393,"AvgDisconnectedness":0.4238054616},{"Player":"vern","CommunityID":4,"Disconnectedness":0.9691634393,"AvgDisconnectedness":0.4238054616},{"Player":"scott ?","CommunityID":4,"Disconnectedness":0.4914155294,"AvgDisconnectedness":0.4238054616},{"Player":"mickey ?","CommunityID":4,"Disconnectedness":0.4886220016,"AvgDisconnectedness":0.4238054616},{"Player":"gene g","CommunityID":4,"Disconnectedness":0.4839586956,"AvgDisconnectedness":0.4238054616},{"Player":"arsen o","CommunityID":4,"Disconnectedness":0.483842445,"AvgDisconnectedness":0.4238054616},{"Player":"jason s","CommunityID":4,"Disconnectedness":0.4819073816,"AvgDisconnectedness":0.4238054616},{"Player":"roger p","CommunityID":4,"Disconnectedness":0.3622507674,"AvgDisconnectedness":0.4238054616},{"Player":"david h","CommunityID":4,"Disconnectedness":0.3268302391,"AvgDisconnectedness":0.4238054616},{"Player":"hilda h","CommunityID":4,"Disconnectedness":0.3268302391,"AvgDisconnectedness":0.4238054616},{"Player":"dallas h","CommunityID":4,"Disconnectedness":0.3265687576,"AvgDisconnectedness":0.4238054616},{"Player":"dr z","CommunityID":4,"Disconnectedness":0.3190489256,"AvgDisconnectedness":0.4238054616},{"Player":"bree s","CommunityID":4,"Disconnectedness":0.2448664535,"AvgDisconnectedness":0.4238054616},{"Player":"robyn h","CommunityID":4,"Disconnectedness":0.1966960036,"AvgDisconnectedness":0.4238054616},{"Player":"alex a","CommunityID":4,"Disconnectedness":0.1942980925,"AvgDisconnectedness":0.4238054616},{"Player":"drew ?","CommunityID":4,"Disconnectedness":0.1396366557,"AvgDisconnectedness":0.4238054616},{"Player":"mike e","CommunityID":4,"Disconnectedness":0.0536819063,"AvgDisconnectedness":0.4238054616},{"Player":"ben l","CommunityID":4,"Disconnectedness":0.0500999482,"AvgDisconnectedness":0.4238054616},{"Player":"marty c","CommunityID":4,"Disconnectedness":0.0431517195,"AvgDisconnectedness":0.4238054616},{"Player":"kay l","CommunityID":4,"Disconnectedness":0.0401930059,"AvgDisconnectedness":0.4238054616},{"Player":"will l","CommunityID":4,"Disconnectedness":0.0383814584,"AvgDisconnectedness":0.4238054616},{"Player":"milan m","CommunityID":4,"Disconnectedness":0.0355340038,"AvgDisconnectedness":0.4238054616},{"Player":"dmitry l","CommunityID":4,"Disconnectedness":0.0302922886,"AvgDisconnectedness":0.4238054616},{"Player":"john e","CommunityID":4,"Disconnectedness":0.0225981394,"AvgDisconnectedness":0.4238054616},{"Player":"marina d","CommunityID":4,"Disconnectedness":0.0224386868,"AvgDisconnectedness":0.4238054616},{"Player":"carol f","CommunityID":4,"Disconnectedness":0.0223870182,"AvgDisconnectedness":0.4238054616},{"Player":"gene d","CommunityID":4,"Disconnectedness":0.0202522443,"AvgDisconnectedness":0.4238054616},{"Player":"lori h","CommunityID":4,"Disconnectedness":0.0052955373,"AvgDisconnectedness":0.4238054616},{"Player":"greg h","CommunityID":4,"Disconnectedness":0.0007759802,"AvgDisconnectedness":0.4238054616},{"Player":"rob h","CommunityID":4,"Disconnectedness":0.0,"AvgDisconnectedness":0.4238054616},{"Player":"kay kay","CommunityID":5,"Disconnectedness":0.9844756476,"AvgDisconnectedness":0.4226060807},{"Player":"carlee","CommunityID":5,"Disconnectedness":0.9831349289,"AvgDisconnectedness":0.4226060807},{"Player":"dale p","CommunityID":5,"Disconnectedness":0.982942011,"AvgDisconnectedness":0.4226060807},{"Player":"joe c","CommunityID":5,"Disconnectedness":0.982942011,"AvgDisconnectedness":0.4226060807},{"Player":"mike legg","CommunityID":5,"Disconnectedness":0.9816254644,"AvgDisconnectedness":0.4226060807},{"Player":"ben n","CommunityID":5,"Disconnectedness":0.9801884201,"AvgDisconnectedness":0.4226060807},{"Player":"amy c","CommunityID":5,"Disconnectedness":0.9797144725,"AvgDisconnectedness":0.4226060807},{"Player":"chris c","CommunityID":5,"Disconnectedness":0.9797144725,"AvgDisconnectedness":0.4226060807},{"Player":"mike s","CommunityID":5,"Disconnectedness":0.9785975063,"AvgDisconnectedness":0.4226060807},{"Player":"enea ?","CommunityID":5,"Disconnectedness":0.9773433169,"AvgDisconnectedness":0.4226060807},{"Player":"james p","CommunityID":5,"Disconnectedness":0.9763120223,"AvgDisconnectedness":0.4226060807},{"Player":"jerome k","CommunityID":5,"Disconnectedness":0.9739441929,"AvgDisconnectedness":0.4226060807},{"Player":"noel l","CommunityID":5,"Disconnectedness":0.9729244327,"AvgDisconnectedness":0.4226060807},{"Player":"trevyn f","CommunityID":5,"Disconnectedness":0.9725360978,"AvgDisconnectedness":0.4226060807},{"Player":"adrian c","CommunityID":5,"Disconnectedness":0.9719106791,"AvgDisconnectedness":0.4226060807},{"Player":"brian h","CommunityID":5,"Disconnectedness":0.9718800885,"AvgDisconnectedness":0.4226060807},{"Player":"joe r","CommunityID":5,"Disconnectedness":0.9718800885,"AvgDisconnectedness":0.4226060807},{"Player":"hunter ?","CommunityID":5,"Disconnectedness":0.9718170138,"AvgDisconnectedness":0.4226060807},{"Player":"kevin h","CommunityID":5,"Disconnectedness":0.971625855,"AvgDisconnectedness":0.4226060807},{"Player":"jack s","CommunityID":5,"Disconnectedness":0.9714473196,"AvgDisconnectedness":0.4226060807},{"Player":"michelle g","CommunityID":5,"Disconnectedness":0.9713734932,"AvgDisconnectedness":0.4226060807},{"Player":"carl ?","CommunityID":5,"Disconnectedness":0.9696626071,"AvgDisconnectedness":0.4226060807},{"Player":"emily ?","CommunityID":5,"Disconnectedness":0.9696626071,"AvgDisconnectedness":0.4226060807},{"Player":"katie ?","CommunityID":5,"Disconnectedness":0.9696626071,"AvgDisconnectedness":0.4226060807},{"Player":"jordan p","CommunityID":5,"Disconnectedness":0.96928903,"AvgDisconnectedness":0.4226060807},{"Player":"lisa h","CommunityID":5,"Disconnectedness":0.968265901,"AvgDisconnectedness":0.4226060807},{"Player":"spencer l","CommunityID":5,"Disconnectedness":0.4962012388,"AvgDisconnectedness":0.4226060807},{"Player":"brian d","CommunityID":5,"Disconnectedness":0.495411115,"AvgDisconnectedness":0.4226060807},{"Player":"jennifer c","CommunityID":5,"Disconnectedness":0.4950697043,"AvgDisconnectedness":0.4226060807},{"Player":"brandon i","CommunityID":5,"Disconnectedness":0.4926500279,"AvgDisconnectedness":0.4226060807},{"Player":"brita w","CommunityID":5,"Disconnectedness":0.4914476584,"AvgDisconnectedness":0.4226060807},{"Player":"gary g","CommunityID":5,"Disconnectedness":0.4901055612,"AvgDisconnectedness":0.4226060807},{"Player":"jalani d","CommunityID":5,"Disconnectedness":0.4858811788,"AvgDisconnectedness":0.4226060807},{"Player":"steve j","CommunityID":5,"Disconnectedness":0.482953541,"AvgDisconnectedness":0.4226060807},{"Player":"ray l","CommunityID":5,"Disconnectedness":0.481720962,"AvgDisconnectedness":0.4226060807},{"Player":"brandon h","CommunityID":5,"Disconnectedness":0.4803564493,"AvgDisconnectedness":0.4226060807},{"Player":"nathan l","CommunityID":5,"Disconnectedness":0.3308387944,"AvgDisconnectedness":0.4226060807},{"Player":"oz b","CommunityID":5,"Disconnectedness":0.3232201644,"AvgDisconnectedness":0.4226060807},{"Player":"dave j","CommunityID":5,"Disconnectedness":0.3224048397,"AvgDisconnectedness":0.4226060807},{"Player":"veronica c","CommunityID":5,"Disconnectedness":0.3212817159,"AvgDisconnectedness":0.4226060807},{"Player":"donovan","CommunityID":5,"Disconnectedness":0.3210232004,"AvgDisconnectedness":0.4226060807},{"Player":"david kong","CommunityID":5,"Disconnectedness":0.3194440514,"AvgDisconnectedness":0.4226060807},{"Player":"nicole l","CommunityID":5,"Disconnectedness":0.3194440514,"AvgDisconnectedness":0.4226060807},{"Player":"mercedez m","CommunityID":5,"Disconnectedness":0.3178814299,"AvgDisconnectedness":0.4226060807},{"Player":"tony s","CommunityID":5,"Disconnectedness":0.3163249186,"AvgDisconnectedness":0.4226060807},{"Player":"jared c","CommunityID":5,"Disconnectedness":0.2496861999,"AvgDisconnectedness":0.4226060807},{"Player":"gavin ?","CommunityID":5,"Disconnectedness":0.2467626723,"AvgDisconnectedness":0.4226060807},{"Player":"pat t","CommunityID":5,"Disconnectedness":0.24477759,"AvgDisconnectedness":0.4226060807},{"Player":"amar","CommunityID":5,"Disconnectedness":0.2364745182,"AvgDisconnectedness":0.4226060807},{"Player":"marcus ?","CommunityID":5,"Disconnectedness":0.197123731,"AvgDisconnectedness":0.4226060807},{"Player":"dennis f","CommunityID":5,"Disconnectedness":0.193037732,"AvgDisconnectedness":0.4226060807},{"Player":"lisa v","CommunityID":5,"Disconnectedness":0.184464348,"AvgDisconnectedness":0.4226060807},{"Player":"kris k","CommunityID":5,"Disconnectedness":0.1736547607,"AvgDisconnectedness":0.4226060807},{"Player":"ken l","CommunityID":5,"Disconnectedness":0.1706575535,"AvgDisconnectedness":0.4226060807},{"Player":"wayne c","CommunityID":5,"Disconnectedness":0.1436016025,"AvgDisconnectedness":0.4226060807},{"Player":"ano a","CommunityID":5,"Disconnectedness":0.1300050614,"AvgDisconnectedness":0.4226060807},{"Player":"bryan o","CommunityID":5,"Disconnectedness":0.128184569,"AvgDisconnectedness":0.4226060807},{"Player":"tony smith","CommunityID":5,"Disconnectedness":0.1269004564,"AvgDisconnectedness":0.4226060807},{"Player":"tom k","CommunityID":5,"Disconnectedness":0.0990489016,"AvgDisconnectedness":0.4226060807},{"Player":"steve b","CommunityID":5,"Disconnectedness":0.0897039024,"AvgDisconnectedness":0.4226060807},{"Player":"eric s","CommunityID":5,"Disconnectedness":0.0825055089,"AvgDisconnectedness":0.4226060807},{"Player":"jeremy k","CommunityID":5,"Disconnectedness":0.0770095226,"AvgDisconnectedness":0.4226060807},{"Player":"steph e","CommunityID":5,"Disconnectedness":0.0685267782,"AvgDisconnectedness":0.4226060807},{"Player":"evan d","CommunityID":5,"Disconnectedness":0.0605095015,"AvgDisconnectedness":0.4226060807},{"Player":"tony spenser","CommunityID":5,"Disconnectedness":0.0592075529,"AvgDisconnectedness":0.4226060807},{"Player":"lyle g","CommunityID":5,"Disconnectedness":0.0539146408,"AvgDisconnectedness":0.4226060807},{"Player":"john b","CommunityID":5,"Disconnectedness":0.0507332277,"AvgDisconnectedness":0.4226060807},{"Player":"patty t","CommunityID":5,"Disconnectedness":0.0464729794,"AvgDisconnectedness":0.4226060807},{"Player":"paul p","CommunityID":5,"Disconnectedness":0.0451545843,"AvgDisconnectedness":0.4226060807},{"Player":"katy v","CommunityID":5,"Disconnectedness":0.0429169348,"AvgDisconnectedness":0.4226060807},{"Player":"rick r","CommunityID":5,"Disconnectedness":0.0419047705,"AvgDisconnectedness":0.4226060807},{"Player":"mike t","CommunityID":5,"Disconnectedness":0.0407262946,"AvgDisconnectedness":0.4226060807},{"Player":"paul s","CommunityID":5,"Disconnectedness":0.0400832579,"AvgDisconnectedness":0.4226060807},{"Player":"kevin b","CommunityID":5,"Disconnectedness":0.0376409001,"AvgDisconnectedness":0.4226060807},{"Player":"dave b","CommunityID":5,"Disconnectedness":0.0372509163,"AvgDisconnectedness":0.4226060807},{"Player":"jaye s","CommunityID":5,"Disconnectedness":0.0361289066,"AvgDisconnectedness":0.4226060807},{"Player":"richard m","CommunityID":5,"Disconnectedness":0.029751101,"AvgDisconnectedness":0.4226060807},{"Player":"matt p","CommunityID":5,"Disconnectedness":0.0264374817,"AvgDisconnectedness":0.4226060807},{"Player":"jason h","CommunityID":5,"Disconnectedness":0.026009366,"AvgDisconnectedness":0.4226060807},{"Player":"deathnote l","CommunityID":5,"Disconnectedness":0.0222723056,"AvgDisconnectedness":0.4226060807},{"Player":"rieley p","CommunityID":5,"Disconnectedness":0.0193448151,"AvgDisconnectedness":0.4226060807},{"Player":"bobby c","CommunityID":5,"Disconnectedness":0.0171286931,"AvgDisconnectedness":0.4226060807},{"Player":"evan j","CommunityID":5,"Disconnectedness":0.016391423,"AvgDisconnectedness":0.4226060807},{"Player":"carlee j","CommunityID":5,"Disconnectedness":0.0116826205,"AvgDisconnectedness":0.4226060807},{"Player":"bartman p","CommunityID":5,"Disconnectedness":0.0101569905,"AvgDisconnectedness":0.4226060807},{"Player":"paul cb","CommunityID":5,"Disconnectedness":0.0075072395,"AvgDisconnectedness":0.4226060807},{"Player":"bonnie l","CommunityID":5,"Disconnectedness":0.0067442172,"AvgDisconnectedness":0.4226060807},{"Player":"kasi ?","CommunityID":2,"Disconnectedness":1.0,"AvgDisconnectedness":0.4205578671},{"Player":"orlando ?","CommunityID":2,"Disconnectedness":0.9953214555,"AvgDisconnectedness":0.4205578671},{"Player":"ricky ?","CommunityID":2,"Disconnectedness":0.9946853547,"AvgDisconnectedness":0.4205578671},{"Player":"shawn k","CommunityID":2,"Disconnectedness":0.9946853547,"AvgDisconnectedness":0.4205578671},{"Player":"aj ?","CommunityID":2,"Disconnectedness":0.9941510304,"AvgDisconnectedness":0.4205578671},{"Player":"aj r","CommunityID":2,"Disconnectedness":0.9857875305,"AvgDisconnectedness":0.4205578671},{"Player":"joe f","CommunityID":2,"Disconnectedness":0.9831908457,"AvgDisconnectedness":0.4205578671},{"Player":"britt t","CommunityID":2,"Disconnectedness":0.9827798877,"AvgDisconnectedness":0.4205578671},{"Player":"glenn z","CommunityID":2,"Disconnectedness":0.9792640195,"AvgDisconnectedness":0.4205578671},{"Player":"devin v","CommunityID":2,"Disconnectedness":0.9742493755,"AvgDisconnectedness":0.4205578671},{"Player":"sam c","CommunityID":2,"Disconnectedness":0.973047308,"AvgDisconnectedness":0.4205578671},{"Player":"lisa ?","CommunityID":2,"Disconnectedness":0.9727176161,"AvgDisconnectedness":0.4205578671},{"Player":"wayne l","CommunityID":2,"Disconnectedness":0.9695256951,"AvgDisconnectedness":0.4205578671},{"Player":"luke s","CommunityID":2,"Disconnectedness":0.5012295356,"AvgDisconnectedness":0.4205578671},{"Player":"brian p","CommunityID":2,"Disconnectedness":0.4936152592,"AvgDisconnectedness":0.4205578671},{"Player":"rickey j","CommunityID":2,"Disconnectedness":0.4851383808,"AvgDisconnectedness":0.4205578671},{"Player":"johnny j","CommunityID":2,"Disconnectedness":0.3226386735,"AvgDisconnectedness":0.4205578671},{"Player":"aaron c","CommunityID":2,"Disconnectedness":0.3201644619,"AvgDisconnectedness":0.4205578671},{"Player":"tom z","CommunityID":2,"Disconnectedness":0.2373022083,"AvgDisconnectedness":0.4205578671},{"Player":"chris g","CommunityID":2,"Disconnectedness":0.2266453264,"AvgDisconnectedness":0.4205578671},{"Player":"cole g","CommunityID":2,"Disconnectedness":0.2187303054,"AvgDisconnectedness":0.4205578671},{"Player":"bob g","CommunityID":2,"Disconnectedness":0.1678758763,"AvgDisconnectedness":0.4205578671},{"Player":"igor m","CommunityID":2,"Disconnectedness":0.1621279265,"AvgDisconnectedness":0.4205578671},{"Player":"wendell e","CommunityID":2,"Disconnectedness":0.1093987612,"AvgDisconnectedness":0.4205578671},{"Player":"jawad d","CommunityID":2,"Disconnectedness":0.1046403952,"AvgDisconnectedness":0.4205578671},{"Player":"tim c","CommunityID":2,"Disconnectedness":0.0884022089,"AvgDisconnectedness":0.4205578671},{"Player":"steven u","CommunityID":2,"Disconnectedness":0.0865181672,"AvgDisconnectedness":0.4205578671},{"Player":"eric h","CommunityID":2,"Disconnectedness":0.0672960561,"AvgDisconnectedness":0.4205578671},{"Player":"dawson z","CommunityID":2,"Disconnectedness":0.0629166788,"AvgDisconnectedness":0.4205578671},{"Player":"paul u","CommunityID":2,"Disconnectedness":0.0533126666,"AvgDisconnectedness":0.4205578671},{"Player":"john l","CommunityID":2,"Disconnectedness":0.0518420476,"AvgDisconnectedness":0.4205578671},{"Player":"adam u","CommunityID":2,"Disconnectedness":0.047418847,"AvgDisconnectedness":0.4205578671},{"Player":"kevin m","CommunityID":2,"Disconnectedness":0.0344240946,"AvgDisconnectedness":0.4205578671},{"Player":"damian a","CommunityID":2,"Disconnectedness":0.0316710978,"AvgDisconnectedness":0.4205578671},{"Player":"jarrett f","CommunityID":2,"Disconnectedness":0.0311450431,"AvgDisconnectedness":0.4205578671},{"Player":"zach f","CommunityID":2,"Disconnectedness":0.0308156545,"AvgDisconnectedness":0.4205578671},{"Player":"mike l","CommunityID":2,"Disconnectedness":0.0265853828,"AvgDisconnectedness":0.4205578671},{"Player":"roger w","CommunityID":2,"Disconnectedness":0.0255630481,"AvgDisconnectedness":0.4205578671},{"Player":"charlie t","CommunityID":2,"Disconnectedness":0.0226962184,"AvgDisconnectedness":0.4205578671},{"Player":"wyatt s","CommunityID":2,"Disconnectedness":0.0127948899,"AvgDisconnectedness":0.4205578671},{"Player":"james a","CommunityID":0,"Disconnectedness":0.9753289508,"AvgDisconnectedness":0.3745775691},{"Player":"angelica g","CommunityID":0,"Disconnectedness":0.9742842167,"AvgDisconnectedness":0.3745775691},{"Player":"vikrant punj","CommunityID":0,"Disconnectedness":0.973174863,"AvgDisconnectedness":0.3745775691},{"Player":"johnny s","CommunityID":0,"Disconnectedness":0.9730072739,"AvgDisconnectedness":0.3745775691},{"Player":"reese r","CommunityID":0,"Disconnectedness":0.969447679,"AvgDisconnectedness":0.3745775691},{"Player":"joey ?","CommunityID":0,"Disconnectedness":0.9685998878,"AvgDisconnectedness":0.3745775691},{"Player":"misebah n","CommunityID":0,"Disconnectedness":0.9682195641,"AvgDisconnectedness":0.3745775691},{"Player":"nick d","CommunityID":0,"Disconnectedness":0.9682195641,"AvgDisconnectedness":0.3745775691},{"Player":"nick b","CommunityID":0,"Disconnectedness":0.965226278,"AvgDisconnectedness":0.3745775691},{"Player":"briana g","CommunityID":0,"Disconnectedness":0.9607875067,"AvgDisconnectedness":0.3745775691},{"Player":"charlie tu","CommunityID":0,"Disconnectedness":0.9607875067,"AvgDisconnectedness":0.3745775691},{"Player":"johon k","CommunityID":0,"Disconnectedness":0.9607875067,"AvgDisconnectedness":0.3745775691},{"Player":"corey t","CommunityID":0,"Disconnectedness":0.4868997702,"AvgDisconnectedness":0.3745775691},{"Player":"tony jr","CommunityID":0,"Disconnectedness":0.4855560471,"AvgDisconnectedness":0.3745775691},{"Player":"wesley k","CommunityID":0,"Disconnectedness":0.4853175009,"AvgDisconnectedness":0.3745775691},{"Player":"sarah j","CommunityID":0,"Disconnectedness":0.4843598061,"AvgDisconnectedness":0.3745775691},{"Player":"alex w","CommunityID":0,"Disconnectedness":0.4793591568,"AvgDisconnectedness":0.3745775691},{"Player":"carter ?","CommunityID":0,"Disconnectedness":0.4793591568,"AvgDisconnectedness":0.3745775691},{"Player":"rick a","CommunityID":0,"Disconnectedness":0.3219572235,"AvgDisconnectedness":0.3745775691},{"Player":"rico c","CommunityID":0,"Disconnectedness":0.3214533468,"AvgDisconnectedness":0.3745775691},{"Player":"domanic a","CommunityID":0,"Disconnectedness":0.3213547111,"AvgDisconnectedness":0.3745775691},{"Player":"brandon t","CommunityID":0,"Disconnectedness":0.3138850172,"AvgDisconnectedness":0.3745775691},{"Player":"lupillo r","CommunityID":0,"Disconnectedness":0.2405314625,"AvgDisconnectedness":0.3745775691},{"Player":"joaquin m","CommunityID":0,"Disconnectedness":0.2397187681,"AvgDisconnectedness":0.3745775691},{"Player":"floyd t","CommunityID":0,"Disconnectedness":0.2048303231,"AvgDisconnectedness":0.3745775691},{"Player":"netty u","CommunityID":0,"Disconnectedness":0.1955079263,"AvgDisconnectedness":0.3745775691},{"Player":"darnell w","CommunityID":0,"Disconnectedness":0.1692011378,"AvgDisconnectedness":0.3745775691},{"Player":"brian j","CommunityID":0,"Disconnectedness":0.1414472276,"AvgDisconnectedness":0.3745775691},{"Player":"tracy s","CommunityID":0,"Disconnectedness":0.1386069789,"AvgDisconnectedness":0.3745775691},{"Player":"joe irish","CommunityID":0,"Disconnectedness":0.095377961,"AvgDisconnectedness":0.3745775691},{"Player":"jack d","CommunityID":0,"Disconnectedness":0.0877444943,"AvgDisconnectedness":0.3745775691},{"Player":"clayton a","CommunityID":0,"Disconnectedness":0.0854489882,"AvgDisconnectedness":0.3745775691},{"Player":"jordan h","CommunityID":0,"Disconnectedness":0.0704296843,"AvgDisconnectedness":0.3745775691},{"Player":"mo m","CommunityID":0,"Disconnectedness":0.0660661652,"AvgDisconnectedness":0.3745775691},{"Player":"colton r","CommunityID":0,"Disconnectedness":0.0630145274,"AvgDisconnectedness":0.3745775691},{"Player":"zach c","CommunityID":0,"Disconnectedness":0.0606378307,"AvgDisconnectedness":0.3745775691},{"Player":"john s","CommunityID":0,"Disconnectedness":0.0584046825,"AvgDisconnectedness":0.3745775691},{"Player":"mellisa h","CommunityID":0,"Disconnectedness":0.0413669768,"AvgDisconnectedness":0.3745775691},{"Player":"brandon c","CommunityID":0,"Disconnectedness":0.0322858633,"AvgDisconnectedness":0.3745775691},{"Player":"adam m","CommunityID":0,"Disconnectedness":0.0275095162,"AvgDisconnectedness":0.3745775691},{"Player":"miguel q","CommunityID":0,"Disconnectedness":0.0271284251,"AvgDisconnectedness":0.3745775691},{"Player":"devon t","CommunityID":0,"Disconnectedness":0.0268311058,"AvgDisconnectedness":0.3745775691},{"Player":"nico a","CommunityID":0,"Disconnectedness":0.026657177,"AvgDisconnectedness":0.3745775691},{"Player":"steel neil","CommunityID":0,"Disconnectedness":0.0231571463,"AvgDisconnectedness":0.3745775691},{"Player":"mercedes m","CommunityID":0,"Disconnectedness":0.0223773844,"AvgDisconnectedness":0.3745775691},{"Player":"jeremiah td","CommunityID":0,"Disconnectedness":0.015630776,"AvgDisconnectedness":0.3745775691},{"Player":"tony sr","CommunityID":0,"Disconnectedness":0.0155546657,"AvgDisconnectedness":0.3745775691},{"Player":"bob r","CommunityID":0,"Disconnectedness":0.0068835897,"AvgDisconnectedness":0.3745775691}]