[{"Player":"bill e","AVG ROI":"94.39%","Rounds Played":46},{"Player":"evan j","AVG ROI":"91.46%","Rounds Played":56},{"Player":"bobby c","AVG ROI":"55.45%","Rounds Played":47},{"Player":"matt p","AVG ROI":"53.49%","Rounds Played":59},{"Player":"miguel q","AVG ROI":"50.90%","Rounds Played":42},{"Player":"jarrett f","AVG ROI":"44.99%","Rounds Played":43},{"Player":"troy r","AVG ROI":"41.13%","Rounds Played":128},{"Player":"geralyn g","AVG ROI":"23.05%","Rounds Played":40},{"Player":"john f","AVG ROI":"22.20%","Rounds Played":83},{"Player":"lori h","AVG ROI":"20.39%","Rounds Played":88},{"Player":"cindy r","AVG ROI":"17.61%","Rounds Played":117},{"Player":"greg h","AVG ROI":"10.08%","Rounds Played":110},{"Player":"jeremiah td","AVG ROI":"9.23%","Rounds Played":47},{"Player":"rob h","AVG ROI":"8.90%","Rounds Played":124},{"Player":"steel neil","AVG ROI":"7.57%","Rounds Played":39},{"Player":"rieley p","AVG ROI":"4.98%","Rounds Played":39},{"Player":"carlee j","AVG ROI":"2.35%","Rounds Played":51},{"Player":"mike l","AVG ROI":"-2.48%","Rounds Played":51},{"Player":"greg s","AVG ROI":"-3.66%","Rounds Played":45},{"Player":"bartman p","AVG ROI":"-12.14%","Rounds Played":80},{"Player":"bonnie l","AVG ROI":"-19.43%","Rounds Played":93},{"Player":"charlie t","AVG ROI":"-20.67%","Rounds Played":66},{"Player":"paul cb","AVG ROI":"-20.90%","Rounds Played":72},{"Player":"damian a","AVG ROI":"-22.70%","Rounds Played":39},{"Player":"ben d","AVG ROI":"-22.93%","Rounds Played":85},{"Player":"roger w","AVG ROI":"-26.12%","Rounds Played":47},{"Player":"bob r","AVG ROI":"-26.57%","Rounds Played":73},{"Player":"pyerre l","AVG ROI":"-27.54%","Rounds Played":100},{"Player":"johnathan h","AVG ROI":"-30.67%","Rounds Played":62},{"Player":"wyatt s","AVG ROI":"-44.27%","Rounds Played":60},{"Player":"tony sr","AVG ROI":"-46.22%","Rounds Played":52},{"Player":"caleb g","AVG ROI":"-49.87%","Rounds Played":73},{"Player":"zach f","AVG ROI":"-53.36%","Rounds Played":45},{"Player":"amar n","AVG ROI":"-79.07%","Rounds Played":48}]