[{"Player":"evan j","AVG ROI":"87.10%","Rounds Played":122},{"Player":"kevin m","AVG ROI":"75.71%","Rounds Played":155},{"Player":"aj l","AVG ROI":"74.95%","Rounds Played":70},{"Player":"bobby c","AVG ROI":"50.68%","Rounds Played":160},{"Player":"bill e","AVG ROI":"43.33%","Rounds Played":102},{"Player":"matt p","AVG ROI":"43.13%","Rounds Played":83},{"Player":"lori h","AVG ROI":"36.94%","Rounds Played":168},{"Player":"cindy r","AVG ROI":"32.16%","Rounds Played":215},{"Player":"john f","AVG ROI":"31.03%","Rounds Played":167},{"Player":"adam m","AVG ROI":"27.27%","Rounds Played":69},{"Player":"troy r","AVG ROI":"21.01%","Rounds Played":233},{"Player":"dawson z","AVG ROI":"17.89%","Rounds Played":73},{"Player":"richard m","AVG ROI":"15.47%","Rounds Played":88},{"Player":"jeremiah td","AVG ROI":"14.74%","Rounds Played":107},{"Player":"jarrett f","AVG ROI":"13.57%","Rounds Played":91},{"Player":"greg h","AVG ROI":"13.07%","Rounds Played":232},{"Player":"carlee j","AVG ROI":"10.55%","Rounds Played":109},{"Player":"rob h","AVG ROI":"8.31%","Rounds Played":239},{"Player":"geralyn g","AVG ROI":"3.25%","Rounds Played":73},{"Player":"mike l","AVG ROI":"1.49%","Rounds Played":82},{"Player":"paul cb","AVG ROI":"-0.96%","Rounds Played":153},{"Player":"greg s","AVG ROI":"-2.07%","Rounds Played":72},{"Player":"bartman p","AVG ROI":"-3.74%","Rounds Played":157},{"Player":"charlie t","AVG ROI":"-5.79%","Rounds Played":130},{"Player":"rieley p","AVG ROI":"-6.22%","Rounds Played":76},{"Player":"damian a","AVG ROI":"-7.30%","Rounds Played":74},{"Player":"roger w","AVG ROI":"-8.86%","Rounds Played":114},{"Player":"bonnie l","AVG ROI":"-12.68%","Rounds Played":205},{"Player":"caleb g","AVG ROI":"-13.01%","Rounds Played":162},{"Player":"johnathan h","AVG ROI":"-13.20%","Rounds Played":121},{"Player":"ben d","AVG ROI":"-16.09%","Rounds Played":163},{"Player":"gene d","AVG ROI":"-17.01%","Rounds Played":93},{"Player":"marina d","AVG ROI":"-20.58%","Rounds Played":92},{"Player":"wyatt s","AVG ROI":"-24.15%","Rounds Played":118},{"Player":"donovan b","AVG ROI":"-27.60%","Rounds Played":105},{"Player":"tony sr","AVG ROI":"-28.49%","Rounds Played":117},{"Player":"pyerre l","AVG ROI":"-28.55%","Rounds Played":189},{"Player":"mason g","AVG ROI":"-31.07%","Rounds Played":86},{"Player":"bob r","AVG ROI":"-32.57%","Rounds Played":110},{"Player":"ken h","AVG ROI":"-43.53%","Rounds Played":101},{"Player":"zach f","AVG ROI":"-45.18%","Rounds Played":95},{"Player":"amar n","AVG ROI":"-50.00%","Rounds Played":145},{"Player":"john l","AVG ROI":"-53.13%","Rounds Played":116},{"Player":"cristiana l","AVG ROI":"-68.78%","Rounds Played":61},{"Player":"deathnote l","AVG ROI":"-74.34%","Rounds Played":69}]